aiohttp_sse/__init__.py
aiohttp_sse/helpers.py
aiohttp_sse/py.typed
aiohttp_sse-2.2.0.dist-info/LICENSE
aiohttp_sse-2.2.0.dist-info/METADATA
aiohttp_sse-2.2.0.dist-info/WHEEL
aiohttp_sse-2.2.0.dist-info/top_level.txt
aiohttp_sse-2.2.0.dist-info/RECORD
