Metadata-Version: 2.1
Name: aiohttp-sse
Version: 2.2.0
Summary: Server-sent events  support for aiohttp.
Home-page: https://github.com/aio-libs/aiohttp_sse/
Author: Nikolay Novik
Author-email: nickolainovik@gmail.com
License: Apache 2
Classifier: License :: OSI Approved :: Apache Software License
Classifier: Intended Audience :: Developers
Classifier: Programming Language :: Python
Classifier: Programming Language :: Python :: 3
Classifier: Programming Language :: Python :: 3.8
Classifier: Programming Language :: Python :: 3.9
Classifier: Programming Language :: Python :: 3.10
Classifier: Programming Language :: Python :: 3.11
Classifier: Programming Language :: Python :: 3.12
Classifier: Topic :: Internet :: WWW/HTTP
Classifier: Framework :: AsyncIO
Classifier: Framework :: aiohttp
Requires-Python: >=3.8
License-File: LICENSE
Requires-Dist: aiohttp>=3.0
